barch/__init__.py
barch/client.py
barch/endpoints.py
barch/enums/__init__.py
barch/enums/base.py
barch/enums/character.py
barch/models/__init__.py
barch/models/base.py
barch/models/character.py
barch/models/http.py
barch/models/raid.py
barch/models/route.py
barch/result.py
barch/serializer.py
barch/services/__init__.py
barch/services/base.py
barch/services/character.py
barch/services/http.py
barch/services/raid.py
barch_py-0.1.0.dist-info/METADATA
barch_py-0.1.0.dist-info/WHEEL
barch_py-0.1.0.dist-info/RECORD
