Metadata-Version: 2.1
Name: barch-py
Version: 0.1.0
Summary: 
Author: Sagar
Author-email: 67011477+thevenuz@users.noreply.github.com
Requires-Python: >=3.10,<4.0
Classifier: Programming Language :: Python :: 3
Classifier: Programming Language :: Python :: 3.10
Classifier: Programming Language :: Python :: 3.11
Requires-Dist: aiohttp (>=3.8.5,<4.0.0)
Requires-Dist: attrs (>=23.1.0,<24.0.0)
